onion_server.py
onion_server-0.0.3.dist-info/LICENCE.txt
onion_server-0.0.3.dist-info/METADATA
onion_server-0.0.3.dist-info/WHEEL
onion_server-0.0.3.dist-info/entry_points.txt
onion_server-0.0.3.dist-info/top_level.txt
onion_server-0.0.3.dist-info/RECORD
