Metadata-Version: 2.1
Name: onion-server
Version: 0.0.3
Summary: Dot-Onion (domain.onion) DeepWeb and Hidden Services Server Manager
Author: Erasmus A. Junior
Author-email: eirasmx@pm.me
License: MIT
Keywords: tor,hosting,onion,hidden,services,server
Classifier: Development Status :: 3 - Alpha
Classifier: Environment :: Console
Classifier: License :: OSI Approved :: MIT License
Classifier: Operating System :: Unix
Classifier: Programming Language :: Python :: 3
Requires-Python: >=3.7
License-File: LICENCE.txt
Requires-Dist: colorama
